convert_markdown/__init__.py
convert_markdown/core/chart_handler.py
convert_markdown/core/converter.py
convert_markdown/exporters/__init__.py
convert_markdown/exporters/docx.py
convert_markdown/exporters/html.py
convert_markdown/exporters/pdf.py
convert_markdown/exporters/pptx.py
convert_markdown/static/styles.py
convert_markdown-0.1.5.dist-info/licenses/LICENSE
convert_markdown-0.1.5.dist-info/METADATA
convert_markdown-0.1.5.dist-info/WHEEL
convert_markdown-0.1.5.dist-info/top_level.txt
convert_markdown-0.1.5.dist-info/RECORD
