Metadata-Version: 2.4
Name: convert-markdown
Version: 0.1.5
Summary: Convert Markdown into HTML, PDF, and other formats with executed code blocks. Display charts and graphs.
Author-email: dgo8 <your.email@example.com>
Project-URL: Homepage, https://github.com/dgo8/convert-markdown
Project-URL: Bug Tracker, https://github.com/dgo8/convert-markdown/issues
Classifier: Programming Language :: Python :: 3
Classifier: License :: OSI Approved :: MIT License
Classifier: Operating System :: OS Independent
Requires-Python: >=3.8
License-File: LICENSE
Requires-Dist: markdown>=3.3.0
Requires-Dist: beautifulsoup4>=4.9.0
Requires-Dist: plotly>=5.0.0
Requires-Dist: matplotlib>=3.4.0
Requires-Dist: numpy>=1.20.0
Requires-Dist: pandas>=1.3.0
Requires-Dist: python-pptx>=0.6.0
Requires-Dist: pdf2docx>=0.5.0
Requires-Dist: weasyprint>=54.0
Requires-Dist: seaborn>=0.11.0
Requires-Dist: kaleido>=0.2.0
Requires-Dist: pymdown-extensions>=10.0
Dynamic: license-file
